mytunes/__init__.py
mytunes/app.py
mytunes_pro-2.0.5.dist-info/licenses/LICENSE
mytunes_pro-2.0.5.dist-info/METADATA
mytunes_pro-2.0.5.dist-info/WHEEL
mytunes_pro-2.0.5.dist-info/entry_points.txt
mytunes_pro-2.0.5.dist-info/top_level.txt
mytunes_pro-2.0.5.dist-info/RECORD
