Metadata-Version: 2.4
Name: mytunes-pro
Version: 2.0.5
Summary: A lightweight, keyboard-centric terminal player for streaming YouTube music.
Author-email: loxo <loxo5432@gmail.com>
Project-URL: Homepage, https://github.com/postgresql-co-kr/mytunes
Project-URL: Bug Tracker, https://github.com/postgresql-co-kr/mytunes/issues
Classifier: Programming Language :: Python :: 3
Classifier: License :: OSI Approved :: MIT License
Classifier: Operating System :: OS Independent
Classifier: Topic :: Multimedia :: Sound/Audio :: Players
Requires-Python: >=3.9
License-File: LICENSE
Requires-Dist: requests
Requires-Dist: urllib3<2.0.0
Requires-Dist: yt-dlp
Requires-Dist: pusher
Dynamic: license-file
